{
  "swagger": "2.0",
  "info": {
    "title": "Contacts Api",
    "descripition": "Contacts Api",
    "version": "1.0.0",
    "description": ""
  },
  "host": "localhost: 3002",
  "basePath": "/",
  "schemes": [
    "https",
    "http"
  ],
  "paths": {
    "/": {
      "get": {
        "description": "",
        "responses": {
          "200": {
            "description": "OK"
          }
        }
      }
    },
    "/api-docs": {
      "get": {
        "description": "",
        "responses": {
          "default": {
            "description": ""
          }
        }
      }
    },
    "/use/": {
      "get": {
        "description": "",
        "produces": [
          "application/json"
        ],
        "responses": {
          "200": {
            "description": "OK"
          }
        }
      },
      "post": {
        "description": "",
        "parameters": [
          {
            "name": "body",
            "in": "body",
            "schema": {
              "type": "object",
              "properties": {
                "firstName": {
                  "example": "any"
                },
                "lastName": {
                  "example": "any"
                },
                "address": {
                  "example": "any"
                },
                "birthday": {
                  "example": "any"
                },
                "email": {
                  "example": "any"
                }
              }
            }
          }
        ],
        "responses": {
          "204": {
            "description": "No Content"
          },
          "500": {
            "description": "Internal Server Error"
          }
        }
      },
      "put": {
        "description": "",
        "parameters": [
          {
            "name": "body",
            "in": "body",
            "schema": {
              "type": "object",
              "properties": {
                "firstName": {
                  "example": "any"
                },
                "lastName": {
                  "example": "any"
                },
                "address": {
                  "example": "any"
                },
                "birthday": {
                  "example": "any"
                },
                "email": {
                  "example": "any"
                }
              }
            }
          }
        ],
        "responses": {
          "204": {
            "description": "No Content"
          },
          "500": {
            "description": "Internal Server Error"
          }
        }
      },
      "delete": {
        "description": "",
        "responses": {
          "204": {
            "description": "No Content"
          },
          "500": {
            "description": "Internal Server Error"
          }
        }
      }
    },
    "/use/{id}": {
      "get": {
        "description": "",
        "produces": [
          "application/json"
        ],
        "parameters": [
          {
            "name": "id",
            "in": "path",
            "required": true,
            "type": "string"
          }
        ],
        "responses": {
          "200": {
            "description": "OK"
          }
        }
      }
    }
  }
}